lacogito/__init__.py
lacogito/sample.py
lacogito-0.0.1.dist-info/LICENSE
lacogito-0.0.1.dist-info/METADATA
lacogito-0.0.1.dist-info/WHEEL
lacogito-0.0.1.dist-info/top_level.txt
lacogito-0.0.1.dist-info/RECORD
