Metadata-Version: 2.1
Name: lacogito
Version: 0.0.1
Summary: Python client for LaCogito
Author-email: Xiaming Chen <chenxm35@gmail.com>
Maintainer-email: Xiaming Chen <chenxm35@gmail.com>
License: Apache License
Project-URL: Homepage, https://github.com/lambdacogito/lacogito-python/
Project-URL: Bug Reports, https://github.com/lambdacogito/lacogito-python/issues
Project-URL: Source, https://github.com/lambdacogito/lacogito-python/
Keywords: AI,AGI,knowledge,reasoning
Classifier: Development Status :: 3 - Alpha
Classifier: Intended Audience :: Developers
Classifier: Topic :: Software Development :: Build Tools
Classifier: License :: OSI Approved :: Apache Software License
Classifier: Programming Language :: Python :: 3
Classifier: Programming Language :: Python :: 3.8
Classifier: Programming Language :: Python :: 3.9
Classifier: Programming Language :: Python :: 3.10
Classifier: Programming Language :: Python :: 3.11
Classifier: Programming Language :: Python :: 3.12
Classifier: Programming Language :: Python :: 3 :: Only
Requires-Python: >=3.8
License-File: LICENSE
Provides-Extra: test
Requires-Dist: coverage ; extra == 'test'
